embcli_openai/__init__.py
embcli_openai/openai.py
embcli_openai/py.typed
embcli_openai-0.1.0.dist-info/METADATA
embcli_openai-0.1.0.dist-info/WHEEL
embcli_openai-0.1.0.dist-info/entry_points.txt
embcli_openai-0.1.0.dist-info/RECORD
